vidtools/__init__.py
vidtools/cmd_help.py
vidtools/cut_video_into_pieces.py
vidtools/file2txt.py
vidtools/main.py
vidtools/pic2vid.py
vidtools/resize_large_gifs.py
vidtools/simple_svg.py
vidtools/svg_animator.py
vidtools/text_animator.py
vidtools/vid2gif.py
vidtools/vid2infinitegif.py
vidtools/vid_compress.py
vidtools/vid_downloader.py
vidtools/vid_transition.py
vidtools/video_to_jpeg_frames.py
vidtools-0.1.2.dist-info/METADATA
vidtools-0.1.2.dist-info/WHEEL
vidtools-0.1.2.dist-info/top_level.txt
vidtools-0.1.2.dist-info/RECORD
