Metadata-Version: 2.1
Name: vidtools
Version: 0.1.2
Summary: video editor scripts
Author: tijgersoftware
Author-email: tijgersoftware@gmail.com
Keywords: python,first package
Classifier: Development Status :: 3 - Alpha
Classifier: Intended Audience :: Education
Classifier: Programming Language :: Python :: 2
Classifier: Programming Language :: Python :: 3
Classifier: Operating System :: MacOS :: MacOS X
Classifier: Operating System :: Microsoft :: Windows
